sphinxcontrib/revealjs/__init__.py
sphinxcontrib/revealjs/addnodes.py
sphinxcontrib/revealjs/builders.py
sphinxcontrib/revealjs/directives/__init__.py
sphinxcontrib/revealjs/directives/incremental.py
sphinxcontrib/revealjs/directives/slides.py
sphinxcontrib/revealjs/directives/speakernote.py
sphinxcontrib/revealjs/lib/revealjs/LICENSE
sphinxcontrib/revealjs/lib/revealjs/dist/reset.css
sphinxcontrib/revealjs/lib/revealjs/dist/reveal.css
sphinxcontrib/revealjs/lib/revealjs/dist/reveal.js
sphinxcontrib/revealjs/lib/revealjs/dist/theme/beige.css
sphinxcontrib/revealjs/lib/revealjs/dist/theme/black.css
sphinxcontrib/revealjs/lib/revealjs/dist/theme/blood.css
sphinxcontrib/revealjs/lib/revealjs/dist/theme/fonts/league-gothic/LICENSE
sphinxcontrib/revealjs/lib/revealjs/dist/theme/fonts/league-gothic/league-gothic.css
sphinxcontrib/revealjs/lib/revealjs/dist/theme/fonts/league-gothic/league-gothic.eot
sphinxcontrib/revealjs/lib/revealjs/dist/theme/fonts/league-gothic/league-gothic.ttf
sphinxcontrib/revealjs/lib/revealjs/dist/theme/fonts/league-gothic/league-gothic.woff
sphinxcontrib/revealjs/lib/revealjs/dist/theme/fonts/source-sans-pro/LICENSE
sphinxcontrib/revealjs/lib/revealjs/dist/theme/fonts/source-sans-pro/source-sans-pro-italic.eot
sphinxcontrib/revealjs/lib/revealjs/dist/theme/fonts/source-sans-pro/source-sans-pro-italic.ttf
sphinxcontrib/revealjs/lib/revealjs/dist/theme/fonts/source-sans-pro/source-sans-pro-italic.woff
sphinxcontrib/revealjs/lib/revealjs/dist/theme/fonts/source-sans-pro/source-sans-pro-regular.eot
sphinxcontrib/revealjs/lib/revealjs/dist/theme/fonts/source-sans-pro/source-sans-pro-regular.ttf
sphinxcontrib/revealjs/lib/revealjs/dist/theme/fonts/source-sans-pro/source-sans-pro-regular.woff
sphinxcontrib/revealjs/lib/revealjs/dist/theme/fonts/source-sans-pro/source-sans-pro-semibold.eot
sphinxcontrib/revealjs/lib/revealjs/dist/theme/fonts/source-sans-pro/source-sans-pro-semibold.ttf
sphinxcontrib_revealjs-0.2a0.dist-info/LICENSE
sphinxcontrib_revealjs-0.2a0.dist-info/WHEEL
sphinxcontrib_revealjs-0.2a0.dist-info/METADATA
sphinxcontrib_revealjs-0.2a0.dist-info/RECORD
