Metadata-Version: 2.1
Name: sphinxcontrib-revealjs
Version: 0.2a0
Summary: Build slides with RevealJS.
License: MPL-2.0
Author: Ashley Trinh
Author-email: ashley@hackbrightacademy.com
Requires-Python: >=3.8,<4.0
Classifier: License :: OSI Approved
Classifier: Programming Language :: Python :: 3
Classifier: Programming Language :: Python :: 3.8
Classifier: Programming Language :: Python :: 3.9
Requires-Dist: Sphinx (>=4.1.1,<5.0.0)
Requires-Dist: beautifulsoup4 (>=4.10.0,<5.0.0)
Requires-Dist: cssutils (>=2.3.0,<3.0.0)
